django_graphql_bp/__init__.py
django_graphql_bp/article/__init__.py
django_graphql_bp/article/forms.py
django_graphql_bp/article/models.py
django_graphql_bp/article/schema.py
django_graphql_bp/article/tests.py
django_graphql_bp/article/migrations/__init__.py
django_graphql_bp/core/__init__.py
django_graphql_bp/core/helpers.py
django_graphql_bp/core/imports.py
django_graphql_bp/core/storages.py
django_graphql_bp/graphql/__init__.py
django_graphql_bp/graphql/api.py
django_graphql_bp/graphql/forms.py
django_graphql_bp/graphql/scalars.py
django_graphql_bp/graphql/tests.py
django_graphql_bp/graphql/utils.py
django_graphql_bp/graphql/views.py
django_graphql_bp/graphql/operations/__init__.py
django_graphql_bp/graphql/operations/connections.py
django_graphql_bp/graphql/operations/fields.py
django_graphql_bp/graphql/operations/filters.py
django_graphql_bp/graphql/operations/interfaces.py
django_graphql_bp/graphql/operations/mutations.py
django_graphql_bp/graphql/tests/__init__.py
django_graphql_bp/graphql/tests/builders.py
django_graphql_bp/graphql/tests/cases.py
django_graphql_bp/graphql/tests/constructors.py
django_graphql_bp/user/__init__.py
django_graphql_bp/user/forms.py
django_graphql_bp/user/models.py
django_graphql_bp/user/nodes.py
django_graphql_bp/user/schema.py
django_graphql_bp/user/tests.py
django_graphql_bp/user/migrations/0001_initial.py
django_graphql_bp/user/migrations/__init__.py
django_graphql_bp-1.3.1.dist-info/DESCRIPTION.rst
django_graphql_bp-1.3.1.dist-info/METADATA
django_graphql_bp-1.3.1.dist-info/RECORD
django_graphql_bp-1.3.1.dist-info/WHEEL
django_graphql_bp-1.3.1.dist-info/metadata.json
django_graphql_bp-1.3.1.dist-info/top_level.txt
