Metadata-Version: 2.0
Name: django-graphql-bp
Version: 1.3.1
Summary: Boiler plate for API projects based on Django 2 &amp; graphql (graphene) 2
Home-page: https://github.com/onextech/django-graphql-bp
Author: Artsem Stalavitski
Author-email: a.stalavitski@gmail.com
License: MIT
Keywords: django graphene graphql boilerplate crud user authentication
Platform: UNKNOWN
Requires-Python: >=3
Requires-Dist: boto3 (>=1.5)
Requires-Dist: django (>=2.0)
Requires-Dist: django-autoslug-iplweb (==1.9.4.dev0)
Requires-Dist: django-filter (>=1.1)
Requires-Dist: django-storages (>=1.6)
Requires-Dist: django-uuid-upload-path (>=1.0)
Requires-Dist: graphene-django (>=2.0)
Requires-Dist: pillow (>=5.0)
Requires-Dist: psycopg2-binary (>=2.7)
